AUTHORS.rst
CONTRIBUTING.rst
HISTORY.rst
LICENSE
MANIFEST.in
README.rst
setup.cfg
setup.py
docs/Makefile
docs/authors.rst
docs/conf.py
docs/contributing.rst
docs/history.rst
docs/index.rst
docs/installation.rst
docs/make.bat
docs/readme.rst
docs/usage.rst
m3u_dump/__init__.py
m3u_dump/cli.py
m3u_dump/logging-prod.conf
m3u_dump/logging.conf
m3u_dump/m3u_dump.py
m3u_dump.egg-info/PKG-INFO
m3u_dump.egg-info/SOURCES.txt
m3u_dump.egg-info/dependency_links.txt
m3u_dump.egg-info/entry_points.txt
m3u_dump.egg-info/not-zip-safe
m3u_dump.egg-info/requires.txt
m3u_dump.egg-info/top_level.txt
tests/__init__.py
tests/test_m3u_dump.py