Metadata-Version: 1.1
Name: m3u-dump
Version: 1.0.1
Summary: m3u dump
Home-page: https://github.com/stateya/m3u-dump
Author: Shuuhei Tateya
Author-email: stateya@gmail.com
License: MIT license
Keywords: m3u_dump
Platform: UNKNOWN
Classifier: Development Status :: 2 - Pre-Alpha
Classifier: Intended Audience :: Developers
Classifier: License :: OSI Approved :: MIT License
Classifier: Natural Language :: English
Classifier: Programming Language :: Python :: 3.5
